{"cameraMode":{"drawMode":0,"name":"Shaded","section":"Shading Mode"},"sceneLighting":true,"audioPlay":false,"sceneViewState":{"m_AlwaysRefresh":false,"showFog":true,"showSkybox":true,"showFlares":true,"showImageEffects":true,"showParticleSystems":true,"showVisualEffectGraphs":true,"m_FxEnabled":true},"in2DMode":false,"pivot":{"x":1.7923076152801514,"y":5.276215076446533,"z":12.747339248657227},"rotation":{"x":-0.06172501668334007,"y":0.7920799851417542,"z":-0.601917564868927,"w":-0.0813756212592125},"size":27.969396591186525,"orthographic":false}